portfolio_balancer/__init__.py
portfolio_balancer/main.py
portfolio_balancer-0.1.18.dist-info/LICENSE
portfolio_balancer-0.1.18.dist-info/METADATA
portfolio_balancer-0.1.18.dist-info/WHEEL
portfolio_balancer-0.1.18.dist-info/entry_points.txt
portfolio_balancer-0.1.18.dist-info/RECORD
