Metadata-Version: 2.1
Name: portfolio-balancer
Version: 0.1.18
Summary: A Python script to balance your cryptocurrency portfolio between two currencies using the Binance API.
License: MIT
Author: Meir Michanie
Author-email: meirm@riunx.com
Requires-Python: >=3.9,<4.0
Classifier: License :: OSI Approved :: MIT License
Classifier: Programming Language :: Python :: 3
Classifier: Programming Language :: Python :: 3.9
Classifier: Programming Language :: Python :: 3.10
Classifier: Programming Language :: Python :: 3.11
Requires-Dist: ccxt (>=1.61.72,<2.0.0)
Requires-Dist: rich (>=13.3.2,<14.0.0)
Requires-Dist: toml (>=0.10.2,<0.11.0)
